<?xml version="1.0" encoding="utf-8"?>
<annotation>
	<object>
		<x>539</x>
		<y>350</y>
		<width>44</width>
		<height>40</height>
		<label>worm</label>
	</object>
	<object>
		<x>784</x>
		<y>313</y>
		<width>33</width>
		<height>29</height>
		<label>omega</label>
	</object>
	<object>
		<x>1058</x>
		<y>224</y>
		<width>39</width>
		<height>40</height>
		<label>worm</label>
	</object>
	<object>
		<x>1326</x>
		<y>122</y>
		<width>73</width>
		<height>35</height>
		<label>worm</label>
	</object>
	<object>
		<x>1403</x>
		<y>488</y>
		<width>49</width>
		<height>50</height>
		<label>worm</label>
	</object>
	<object>
		<x>1105</x>
		<y>518</y>
		<width>69</width>
		<height>33</height>
		<label>worm</label>
	</object>
	<object>
		<x>890</x>
		<y>555</y>
		<width>48</width>
		<height>59</height>
		<label>worm</label>
	</object>
	<object>
		<x>632</x>
		<y>624</y>
		<width>51</width>
		<height>69</height>
		<label>worm</label>
	</object>
	<object>
		<x>541</x>
		<y>981</y>
		<width>69</width>
		<height>43</height>
		<label>worm</label>
	</object>
	<object>
		<x>865</x>
		<y>823</y>
		<width>73</width>
		<height>30</height>
		<label>worm</label>
	</object>
	<object>
		<x>1117</x>
		<y>748</y>
		<width>39</width>
		<height>62</height>
		<label>worm</label>
	</object>
	<object>
		<x>1344</x>
		<y>743</y>
		<width>78</width>
		<height>37</height>
		<label>worm</label>
	</object>
	<object>
		<x>520</x>
		<y>307</y>
		<width>150</width>
		<height>148</height>
		<label>droplet</label>
	</object>
	<object>
		<x>742</x>
		<y>240</y>
		<width>150</width>
		<height>156</height>
		<label>droplet</label>
	</object>
	<object>
		<x>983</x>
		<y>195</y>
		<width>162</width>
		<height>159</height>
		<label>droplet</label>
	</object>
	<object>
		<x>1290</x>
		<y>98</y>
		<width>162</width>
		<height>158</height>
		<label>droplet</label>
	</object>
	<object>
		<x>1312</x>
		<y>423</y>
		<width>164</width>
		<height>156</height>
		<label>droplet</label>
	</object>
	<object>
		<x>1300</x>
		<y>689</y>
		<width>162</width>
		<height>160</height>
		<label>droplet</label>
	</object>
	<object>
		<x>1048</x>
		<y>488</y>
		<width>156</width>
		<height>176</height>
		<label>droplet</label>
	</object>
	<object>
		<x>1076</x>
		<y>717</y>
		<width>171</width>
		<height>183</height>
		<label>droplet</label>
	</object>
	<object>
		<x>831</x>
		<y>794</y>
		<width>187</width>
		<height>177</height>
		<label>droplet</label>
	</object>
	<object>
		<x>815</x>
		<y>538</y>
		<width>162</width>
		<height>179</height>
		<label>droplet</label>
	</object>
	<object>
		<x>541</x>
		<y>591</y>
		<width>172</width>
		<height>185</height>
		<label>droplet</label>
	</object>
	<object>
		<x>510</x>
		<y>888</y>
		<width>207</width>
		<height>180</height>
		<label>droplet</label>
	</object>
</annotation>